Metadata-Version: 2.1
Name: fastadmin2
Version: 0.2.6
Summary: 
Home-page: https://github.com/levon2111/fastadmin2
License: MIT
Keywords: fastapi,admin
Author: Levon
Author-email: levon2111@gmail.com
Requires-Python: >=3.10,<4.0
Classifier: Environment :: Console
Classifier: Framework :: Django
Classifier: Framework :: FastAPI
Classifier: Framework :: Flask
Classifier: License :: OSI Approved :: MIT License
Classifier: Operating System :: OS Independent
Classifier: Programming Language :: Python :: 3
Classifier: Programming Language :: Python :: 3.10
Classifier: Programming Language :: Python :: 3.11
Classifier: Programming Language :: Python :: 3.12
Classifier: Topic :: Software Development :: Documentation
Classifier: Topic :: Software Development :: Libraries :: Python Modules
Classifier: Topic :: Software Development :: Widget Sets
Provides-Extra: django
Provides-Extra: fastapi
Provides-Extra: flask
Provides-Extra: pony
Provides-Extra: sqlalchemy
Provides-Extra: tortoise-orm
Requires-Dist: asgiref (==3.6.0)
Requires-Dist: django (==4.*) ; extra == "django"
Requires-Dist: fastapi (==0.*) ; extra == "fastapi"
Requires-Dist: flask (==2.*) ; extra == "flask"
Requires-Dist: greenlet (>=3.0.3,<4.0.0)
Requires-Dist: isort (>=5.12.0,<6.0.0)
Requires-Dist: jinja2 (>=3.1.2,<4.0.0)
Requires-Dist: pony (==0.*) ; extra == "pony"
Requires-Dist: pydantic (>=1.10.7,<2.0.0)
Requires-Dist: pyjwt (>=2.6.0,<3.0.0)
Requires-Dist: python-dotenv (>=1.0.0,<2.0.0)
Requires-Dist: sqlalchemy (==2.*) ; extra == "sqlalchemy"
Requires-Dist: tortoise-orm (==0.*) ; extra == "tortoise-orm"
Project-URL: Repository, https://github.com/levon2111/fastadmin2
